lumeview/__init__.py
lumeview/__main__.py
lumeview/cli/__init__.py
lumeview/cli/main.py
lumeview/core/__init__.py
lumeview/core/loader.py
lumeview/tui/__init__.py
lumeview/tui/app.py
lumeview/tui/box_display.py
lumeview/tui/tree_display.py
lumeview-0.1.1.dist-info/METADATA
lumeview-0.1.1.dist-info/WHEEL
lumeview-0.1.1.dist-info/entry_points.txt
lumeview-0.1.1.dist-info/RECORD
