Metadata-Version: 2.4
Name: lumeview
Version: 0.1.1
Summary: Lume - A beautiful JSON viewer CLI
Project-URL: Homepage, https://github.com/dorochadev/lume
Project-URL: Repository, https://github.com/dorochadev/lume
Project-URL: Issues, https://github.com/dorochadev/lume/issues
Author-email: Dorocha <me@dorocha.dev>
License: MIT
Classifier: Development Status :: 3 - Alpha
Classifier: Intended Audience :: Developers
Classifier: License :: OSI Approved :: MIT License
Classifier: Programming Language :: Python :: 3
Classifier: Programming Language :: Python :: 3.10
Classifier: Programming Language :: Python :: 3.11
Classifier: Programming Language :: Python :: 3.12
Classifier: Topic :: Terminals
Classifier: Topic :: Utilities
Requires-Python: >=3.10
Requires-Dist: click>=8.1.7
Requires-Dist: httpx>=0.28.1
Requires-Dist: rich>=14.2.0
Requires-Dist: textual>=0.85.0
